ibm_watson/__init__.py
ibm_watson/assistant_v1.py
ibm_watson/assistant_v2.py
ibm_watson/authorization_v1.py
ibm_watson/common.py
ibm_watson/compare_comply_v1.py
ibm_watson/discovery_v1.py
ibm_watson/language_translator_v3.py
ibm_watson/natural_language_classifier_v1.py
ibm_watson/natural_language_understanding_v1.py
ibm_watson/personality_insights_v3.py
ibm_watson/speech_to_text_v1.py
ibm_watson/speech_to_text_v1_adapter.py
ibm_watson/text_to_speech_adapter_v1.py
ibm_watson/text_to_speech_v1.py
ibm_watson/tone_analyzer_v3.py
ibm_watson/version.py
ibm_watson/visual_recognition_v3.py
ibm_watson/websocket/__init__.py
ibm_watson/websocket/audio_source.py
ibm_watson/websocket/recognize_abstract_callback.py
ibm_watson/websocket/recognize_listener.py
ibm_watson/websocket/synthesize_callback.py
ibm_watson/websocket/synthesize_listener.py
tiggatts_watson_gsingh-0.0.1.dist-info/METADATA
tiggatts_watson_gsingh-0.0.1.dist-info/WHEEL
tiggatts_watson_gsingh-0.0.1.dist-info/top_level.txt
tiggatts_watson_gsingh-0.0.1.dist-info/RECORD
